LICENSE.txt
README.md
setup.cfg
setup.py
pycrescolib/__init__.py
pycrescolib/admin.py
pycrescolib/agents.py
pycrescolib/api.py
pycrescolib/base_classes.py
pycrescolib/clientlib.py
pycrescolib/dataplane.py
pycrescolib/globalcontroller.py
pycrescolib/logstreamer.py
pycrescolib/messaging.py
pycrescolib/utils.py
pycrescolib/wc_interface.py
pycrescolib.egg-info/PKG-INFO
pycrescolib.egg-info/SOURCES.txt
pycrescolib.egg-info/dependency_links.txt
pycrescolib.egg-info/requires.txt
pycrescolib.egg-info/top_level.txt