Metadata-Version: 2.4
Name: pycrescolib
Version: 0.14
Summary: Python Cresco Client Library
Home-page: http://cresco.io
Author: Cresco Team
Author-email: info@cresco.io
License: Apache 2.0
License-File: LICENSE.txt
Requires-Dist: websockets>=10.0
Requires-Dist: cryptography==44.0.1
Requires-Dist: backoff>=2.0.0
Dynamic: author
Dynamic: author-email
Dynamic: description
Dynamic: description-content-type
Dynamic: home-page
Dynamic: license
Dynamic: license-file
Dynamic: requires-dist
Dynamic: summary
